AUTHORS
LICENSE
MANIFEST.in
README.rst
setup.py
cherrydev/__init__.py
django_cherrydev.egg-info/PKG-INFO
django_cherrydev.egg-info/SOURCES.txt
django_cherrydev.egg-info/dependency_links.txt
django_cherrydev.egg-info/entry_points.txt
django_cherrydev.egg-info/requires.txt
django_cherrydev.egg-info/top_level.txt