Metadata-Version: 1.0
Name: django-cherrydev
Version: 0.1
Summary: CherryPy Web server for Django development.
Home-page: http://code.db-init.com/django-cherrydev/
Author: David Bennett
Author-email: david@db-init.com
License: MIT
Platform: UNKNOWN
Classifier: Development Status :: 4 - Beta
Classifier: Environment :: Web Environment
Classifier: Framework :: Django
Classifier: Intended Audience :: Developers
Classifier: License :: OSI Approved :: MIT License
Classifier: Operating System :: OS Independent
Classifier: Programming Language :: Python :: 2.7
Classifier: Topic :: Software Development :: Libraries :: Python Modules
Classifier: Topic :: Utilities
